{"name":"Airsend Desktop","tagline":"TFG - AirSend Desktop","body":"### ¿Qué es AirSend?\r\nAirSend es una aplicación multiplataforma que permite el intercambio de ficheros entre dispositivos que se encuentren conectados a la misma red de área local.\r\n\r\n### Proyecto AirSend\r\nAirSend es un proyecto de Pablo Toledo Gavagnin <jpablotoledo92@gmail.com> para el Trabajo de Fin de Grado para la titulación de Grado en Ingeniería de Computadores de la Universidad Rey Juan Carlos.\r\n\r\n### Descargar AirSend Desktop\r\n[Descargar AirSend Desktop](https://github.com/pablotoledo/AirSend-Desktop/blob/master/compilacion/AirSend.jar)\r\n\r\n### Versión para Android\r\nTambién es posible hacer uso de AirSend con nuestro dispositivo Android, dentro del siguiente enlace podemos ver el proyecto de la versión para mobile.[Versión para Android](http://pablotoledo.github.io/AirSend-Android/)","google":"","note":"Don't delete this file! It's used internally to help with page regeneration."}